gcloud_storage_manager/__init__.py
gcloud_storage_manager/base.py
gcloud_storage_manager/download.py
gcloud_storage_manager/std_logging.py
gcloud_storage_manager/upload.py
tests/__init__.py
tests/test_download.py
tests/test_upload.py
gcloud_storage_manager-0.2.0.dist-info/LICENSE
gcloud_storage_manager-0.2.0.dist-info/METADATA
gcloud_storage_manager-0.2.0.dist-info/WHEEL
gcloud_storage_manager-0.2.0.dist-info/top_level.txt
gcloud_storage_manager-0.2.0.dist-info/RECORD
