Metadata-Version: 2.1
Name: gcloud-storage-manager
Version: 0.2.0
Summary: A package to manage Google Cloud Storage
Home-page: https://github.com/masatoEmata/gcloud_storage_manager
Author: Masato Emata
Keywords: google cloud storage
Classifier: Development Status :: 5 - Production/Stable
Classifier: License :: OSI Approved :: MIT License
Classifier: Programming Language :: Python :: 3
Classifier: Programming Language :: Python :: 3.10
License-File: LICENSE
